napari_sphinx_theme/__init__.py
napari_sphinx_theme/_version.py
napari_sphinx_theme/footer.html
napari_sphinx_theme/layout.html
napari_sphinx_theme/napari-copyright.html
napari_sphinx_theme/napari-footer-links.html
napari_sphinx_theme/napari_code_theme.py
napari_sphinx_theme/page-toc.html
napari_sphinx_theme/search-button-field.html
napari_sphinx_theme/search-field.html
napari_sphinx_theme/theme.conf
napari_sphinx_theme/partials/github-light-blue.html
napari_sphinx_theme/partials/github-purple.html
napari_sphinx_theme/partials/github.html
napari_sphinx_theme/partials/image-sc-light-blue.html
napari_sphinx_theme/partials/image-sc-purple.html
napari_sphinx_theme/partials/image-sc.html
napari_sphinx_theme/partials/mastodon-light-blue.html
napari_sphinx_theme/partials/mastodon-purple.html
napari_sphinx_theme/partials/mastodon.html
napari_sphinx_theme/partials/menu.html
napari_sphinx_theme/partials/napari-hub-light-blue.html
napari_sphinx_theme/partials/napari-hub-purple.html
napari_sphinx_theme/partials/napari-hub.html
napari_sphinx_theme/partials/napari.html
napari_sphinx_theme/partials/zulip-light-blue.html
napari_sphinx_theme/partials/zulip-purple.html
napari_sphinx_theme/partials/zulip.html
napari_sphinx_theme/static/css/napari-sphinx-theme.css
napari_sphinx_theme-1.0.0.dist-info/licenses/LICENSE
napari_sphinx_theme-1.0.0.dist-info/METADATA
napari_sphinx_theme-1.0.0.dist-info/WHEEL
napari_sphinx_theme-1.0.0.dist-info/entry_points.txt
napari_sphinx_theme-1.0.0.dist-info/top_level.txt
napari_sphinx_theme-1.0.0.dist-info/RECORD
