Metadata-Version: 2.4
Name: napari-sphinx-theme
Version: 1.0.0
Summary: Bootstrap-based Sphinx theme from the napari community
Author: napari team
License-Expression: BSD-3-Clause
Project-URL: homepage, https://napari.org/napari-sphinx-theme/
Project-URL: repository, https://github.com/napari/napari-sphinx-theme
Classifier: Development Status :: 4 - Beta
Classifier: Programming Language :: Python :: 3
Classifier: Framework :: Sphinx
Classifier: Framework :: Sphinx :: Theme
Classifier: Operating System :: OS Independent
Requires-Python: >=3.10
License-File: LICENSE
Requires-Dist: pydata-sphinx-theme>=0.16.1
Requires-Dist: packaging
Requires-Dist: docutils-stubs==0.0.22
Requires-Dist: types-docutils==0.21.0.20250728
Requires-Dist: types-pygments
Provides-Extra: doc
Requires-Dist: numpydoc; extra == "doc"
Requires-Dist: sphinx-design; extra == "doc"
Provides-Extra: dev
Requires-Dist: pyyaml; extra == "dev"
Requires-Dist: pre-commit; extra == "dev"
Requires-Dist: nox; extra == "dev"
Requires-Dist: mypy; extra == "dev"
Requires-Dist: types-docutils; extra == "dev"
Requires-Dist: napari-sphinx-theme[coverage]; extra == "dev"
Dynamic: license-file
